[
  {
    "companyName": "Apple",
    "ticker": "AAPL",
    "slug": "apple",
    "sector": "Technology",
    "domain": "apple.com",
    "currency": "USD",
    "currentPrice": 301.54,
    "marketCap": "4.43T",
    "peRatio": 36.51,
    "dividendYield": 36.0
  },
  {
    "companyName": "Broadcom",
    "ticker": "AVGO",
    "slug": "broadcom",
    "sector": "Technology",
    "domain": "broadcom.com",
    "currency": "USD",
    "currentPrice": 396.6,
    "marketCap": "1.88T",
    "peRatio": 65.77,
    "dividendYield": 66.0
  },
  {
    "companyName": "Cisco Systems",
    "ticker": "CSCO",
    "slug": "cisco",
    "sector": "Technology",
    "domain": "cisco.com",
    "industry": "Networking, Security and Observability",
    "currency": "USD",
    "currentPrice": 124.15,
    "marketCap": "489.33B",
    "marketCapRank": 26,
    "peRatio": 41.38,
    "dividendYield": 135.0,
    "volatilityRating": 3,
    "volatilityLabel": "Moderate / Stable"
  },
  {
    "companyName": "Microsoft",
    "ticker": "MSFT",
    "slug": "microsoft",
    "sector": "Technology",
    "domain": "microsoft.com",
    "currency": "USD",
    "currentPrice": 411.74,
    "marketCap": "3.06T",
    "peRatio": 24.52,
    "dividendYield": 88.0
  },
  {
    "companyName": "Nvidia",
    "ticker": "NVDA",
    "slug": "nvidia",
    "sector": "Technology",
    "domain": "nvidia.com",
    "currency": "USD",
    "currentPrice": 208.64,
    "marketCap": "5.05T",
    "peRatio": 31.95,
    "dividendYield": 48.0
  }
]
